[
  {
    "level": -1,
    "name": "Initiative Roll",
    "type": "BASE",
    "subtype": null,
    "source": "CUSTOM",
    "description": "Base initiative roll (DEX check).",
    "affectedStats": [
      {
        "name": "initiativeTotal",
        "value": "(int)",
        "tags": {"initiative": true},
        "ref": "PHB 189"
      }
    ]
  },
  {
    "level": -1,
    "name": "Dexterity Modifier",
    "type": "MODIFIER",
    "subtype": null,
    "source": "CUSTOM",
    "description": "Modifier based on Dexterity score.",
    "affectedStats": [
      {
        "name": "initiativeTotal",
        "value": "(int)",
        "tags": {"initiative": true},
        "ref": "PHB"
      }
    ]
  },
  {
    "level": -1,
    "name": "Spellcasting",
    "type": "PENALTY",
    "subtype": null,
    "source": "CUSTOM",
    "description": "Speed factor initiative modifier based on spell level.",
    "affectedStats": [
      {
        "name": "initiativeTotal",
        "value": "(int)",
        "tags": {"initiative": true, "speed factor": true, "variant": true},
        "ref": "DMG 270"
      }
    ]
  },
  {
    "level": -1,
    "name": "Melee, heavy weapon",
    "type": "PENALTY",
    "subtype": null,
    "source": "null",
    "description": "Speed factor initiative modifier based on size/weight of weapon.",
    "affectedStats": [
      {
        "name": "initiativeTotal",
        "value": -2,
        "tags": {"initiative": true, "speed factor": true, "variant": true},
        "ref": "DMG 270"
      }
    ]
  },
  {
    "level": -1,
    "name": "Melee, light or finesse weapon",
    "type": "BONUS",
    "subtype": null,
    "source": "null",
    "description": "Speed factor initiative modifier based on size/weight of weapon.",
    "affectedStats": [
      {
        "name": "initiativeTotal",
        "value": 2,
        "tags": {"initiative": true, "speed factor": true, "variant": true},
        "ref": "DMG 270"
      }
    ]
  },
  {
    "level": -1,
    "name": "Melee, two-handed weapon",
    "type": "PENALTY",
    "subtype": null,
    "source": "null",
    "description": "Speed factor initiative modifier based on size/weight of weapon.",
    "affectedStats": [
      {
        "name": "initiativeTotal",
        "value": -2,
        "tags": {"initiative": true, "speed factor": true, "variant": true},
        "ref": "DMG 270"
      }
    ]
  },
  {
    "level": -1,
    "name": "Ranged, loading weapon",
    "type": "PENALTY",
    "subtype": null,
    "source": "null",
    "description": "Speed factor initiative modifier for using a ranged weapon requiring effort to reload.",
    "affectedStats": [
      {
        "name": "initiativeTotal",
        "value": -5,
        "tags": {"initiative": true, "speed factor": true, "variant": true},
        "ref": "DMG 270"
      }
    ]
  },
  {
    "level": -1,
    "name": "Custom Speed Factor Modifier",
    "type": "MODIFIER",
    "subtype": null,
    "source": "CUSTOM",
    "description": "(string)",
    "affectedStats": [
      {
        "name": "initiativeTotal",
        "value": "(int)",
        "tags": {"initiative": true, "speed factor": true, "variant": true},
        "ref": "DMG 270"
      }
    ]
  }
]